<pickledDNA>

  <dna>111/94/102/3/-16/25/-15/0/9/0/0/28/102/5514:86:-1/5018:86:-1/4506:102:102/4006:62:102/6001:110:-1/2501:-1:-1/9:8:-1/3001:-1:-1/502:44:-1/1001:26:-1/1501:-1:-1/3501:26:-1/2002:44:-1</dna>
  <dna>M/100/95/88/0/-8/20/-15/0/12/0/0/28/107/122:19:46/501:37:166/1120:78:21/1501:37:166/2118:37:166/2501:37:-1/3001:37:-1/3592:77:21/4035:63:107/4535:105:-1/5044:77:-1/5547:73:-1/6001:112:166</dna>
  <dna>111/94/95/15/-16/25/-19/0/0/-2/38/0/93/5519:90:-1/5005:90:-1/4501:93:93/4001:58:93/6003:111:-1/2003:47:-1/1016:27:-1/3504:27:-1/520:47:-1/21:137:-1/1508:47:-1/2504:47:-1/3008:47:-1</dna>
  <dna>115/95/88/-10/-110/25/-90/0/6/0/0/28/108/5515:73:-1/5017:73:-1/4508:108:108/4008:55:108/6005:109:-1/2501:-1:-1/3001:-1:-1/3508:33:-1/7:5:-1/2002:37:-1/1501:-1:-1/1013:35:-1/514:47:-1</dna>
  <dna>100/90/88/0/-56/38/-15/0/11/0/70/40/106/5506:89:-1/5005:89:-1/4508:106:106/4008:64:106/6003:109:-1/3501:33:-1/3007:48:-1/2505:48:-1/501:-1:-1/1006:33:-1/1506:48:-1/2001:-1:-1/5:15:-1</dna>
  <dna>100/90/88/-10/-15/35/-55/-52/0/0/70/26/94/5507:74:-1/5019:74:-1/4501:94:94/4001:56:94/6002:111:-1/1508:49:-1/2505:49:-1/2002:49:-1/1013:36:-1/510:49:-1/3008:49:-1/3507:36:-1/9:18:-1</dna>
  <dna>115/95/95/0/-77/32/-38/-17/13/0/20/53/106/5513:80:-1/5006:80:-1/4503:106:106/4003:65:106/6003:110:-1/3001:-1:-1/1503:44:-1/504:44:-1/1001:32:-1/2009:43:-1/5:14:-1/3505:26:-1/2505:44:-1</dna>
  <dna>107/92/95/15/-110/25/-75/-51/4/-15/0/83/108/5509:80:-1/5010:80:-1/4506:108:108/4006:72:108/6006:109:-1/1002:32:-1/3001:-1:-1/1507:37:-1/504:37:-1/2012:45:-1/5:15:-1/2504:37:-1/3506:32:-1</dna>
  <dna>108/93/88/-10/-15/25/0/0/5/-3/7/29/103/5511:81:-1/5010:81:-1/4505:103:103/4005:69:103/6003:110:-1/2505:53:-1/3508:26:-1/2002:54:-1/1508:44:-1/14:8:-1/1006:26:-1/501:-1:-1/3008:44:-1</dna>
  <dna>100/90/88/15/-110/75/-4/-7/15/0/0/70/108/5516:74:-1/5012:74:-1/4501:108:108/4001:67:108/6006:111:-1/506:37:-1/9:16:-1/1508:37:-1/3508:34:-1/3008:37:-1/2015:37:-1/2505:37:-1/1014:19:-1</dna>
  <dna>112/94/92/-10/-19/29/-6/-12/4/-8/15/36/102/5513:79:-1/5014:79:-1/4501:102:102/4001:70:102/6004:112:-1/3503:35:-1/2515:53:-1/1502:53:-1/501:-1:-1/1021:35:-1/3:17:-1/2016:41:-1/3002:53:-1</dna>
  <dna>100/90/95/0/-16/25/-15/0/6/0/0/28/95/5501:74:-1/5014:74:-1/4508:95:95/4008:55:95/6005:111:-1/502:45:-1/3507:31:-1/2015:45:-1/1001:29:-1/1:11:-1/2511:45:-1/3008:45:-1/1508:45:-1</dna>
  <dna>109/93/93/-1/-15/25/0/-52/15/-15/0/90/107/5513:75:-1/5015:75:-1/4510:107:107/4010:56:107/6002:112:-1/2011:37:-1/2511:42:-1/19:4:-1/3008:42:-1/1508:42:-1/1017:22:-1/502:37:-1/3501:24:-1</dna>
  <dna>100/90/88/15/-26/25/-15/0/0/0/70/26/107/5513:86:-1/5019:86:-1/4512:107:107/4012:69:107/6003:112:-1/3502:24:-1/513:37:-1/1508:37:-1/2505:37:-1/5:6:-1/2004:37:-1/3008:37:-1/1009:24:-1</dna>
  <dna>110/93/101/0/-16/25/-15/0/6/0/0/28/93/5519:74:-1/5010:74:-1/4502:93:93/4002:57:93/6002:111:-1/2501:-1:-1/3:11:-1/3001:-1:-1/3502:27:-1/1501:-1:-1/2012:48:-1/1002:29:-1/502:38:-1</dna>
  <dna>107/92/95/0/-16/25/-15/0/6/0/0/28/107/5508:90:-1/5009:90:-1/4518:107:107/4018:67:107/6004:112:-1/2501:-1:-1/3001:-1:-1/1014:24:-1/4:6:-1/2005:42:-1/502:42:-1/1501:-1:-1/3503:24:-1</dna>
  <dna>113/94/98/12/-28/30/-25/0/6/-6/0/35/103/5501:77:-1/5003:77:-1/4506:103:103/4006:62:103/6001:109:-1/502:41:-1/3001:-1:-1/3502:28:-1/1014:21:-1/1501:-1:-1/4:2:-1/2503:41:-1/2012:41:-1</dna>
  <dna>100/90/88/-10/-110/75/-67/0/15/-15/70/0/106/5503:83:-1/5014:83:-1/4505:106:106/4005:64:106/6004:110:-1/6:12:-1/1002:21:-1/2504:47:-1/2005:39:-1/3505:21:-1/504:38:-1/3006:47:-1/1503:47:-1</dna>
  <dna>115/95/88/3/-16/25/-15/0/6/0/0/28/106/5508:88:-1/5010:88:-1/4518:106:106/4018:62:106/6002:111:-1/1020:27:-1/2003:47:-1/1506:47:-1/2505:47:-1/501:-1:-1/3508:34:-1/3007:47:-1/16:16:-1</dna>
  <dna>111/94/100/-2/-16/25/-15/0/5/-1/0/44/101/5515:76:-1/5008:76:-1/4504:101:101/4004:66:101/6004:110:-1/3001:-1:-1/2002:54:-1/2510:54:-1/502:46:-1/1001:25:-1/3506:28:-1/1502:54:-1/1:7:-1</dna>
  <dna>114/95/100/0/-16/25/-15/0/6/0/0/28/100/5514:90:-1/5017:90:-1/4505:100:100/4005:67:100/6004:110:-1/3501:20:-1/14:2:-1/2504:40:-1/3002:40:-1/2012:40:-1/502:40:-1/1001:20:-1/1502:40:-1</dna>
  <dna>113/94/100/4/-43/54/-24/0/9/-3/4/9/95/5521:73:-1/5004:73:-1/4504:95:95/4004:61:95/6004:112:-1/3001:-1:-1/2010:41:-1/1011:24:-1/3502:24:-1/503:41:-1/1501:-1:-1/3:13:-1/2504:41:-1</dna>
  <dna>110/93/98/-10/-57/59/-90/-52/0/-15/0/55/95/5506:78:-1/5017:78:-1/4508:95:95/4008:69:95/6006:111:-1/3002:42:-1/1502:42:-1/2002:53:-1/4:14:-1/513:41:-1/2503:54:-1/3505:32:-1/1014:31:-1</dna>
  <dna>109/93/96/6/-16/49/-47/-16/9/0/53/28/96/5506:77:-1/5010:77:-1/4506:96:96/4006:71:96/6004:109:-1/3001:-1:-1/1:5:-1/1502:37:-1/501:-1:-1/3502:28:-1/1014:23:-1/2001:-1:-1/2504:37:-1</dna>
  <dna>112/94/98/-5/-28/33/-12/-37/12/0/70/28/102/5506:73:-1/5003:73:-1/4501:102:102/4001:63:102/6003:112:-1/3001:-1:-1/1005:21:-1/3506:21:-1/1501:-1:-1/3:2:-1/513:41:-1/2002:53:-1/2502:37:-1</dna>
  <dna>111/94/102/6/-15/25/-21/-2/10/-2/7/46/107/5513:81:-1/5005:81:-1/4509:107:107/4009:59:107/6005:112:-1/2504:42:-1/3006:41:-1/3508:31:-1/1021:31:-1/1501:-1:-1/19:13:-1/521:41:-1/2016:41:-1</dna>
  <dna>107/92/97/-7/-16/25/-45/0/6/0/0/37/106/5512:74:-1/5014:74:-1/4501:106:106/4001:56:106/6005:112:-1/509:50:-1/1501:-1:-1/1008:35:-1/2515:50:-1/3505:24:-1/3008:47:-1/19:17:-1/2010:50:-1</dna>
  <dna>115/95/88/0/-83/42/-54/0/5/-15/21/77/107/5514:81:-1/5005:81:-1/4514:107:107/4014:67:107/6006:109:-1/2501:-1:-1/3009:48:-1/3506:141:-1/5:141:-1/517:48:-1/1004:30:-1/2012:48:-1/1509:48:-1</dna>
  <dna>104/91/94/0/-17/25/-45/0/5/0/70/32/106/5510:79:-1/5003:79:-1/4501:106:106/4001:70:106/6004:109:-1/1504:37:-1/2507:37:-1/3:12:-1/3503:30:-1/513:37:-1/2001:-1:-1/3006:37:-1/1001:30:-1</dna>
  <dna>115/95/102/0/-15/59/-73/-36/0/-1/17/80/107/5514:88:-1/5010:88:-1/4501:107:107/4001:63:107/6006:111:-1/2501:-1:-1/3:5:-1/2004:47:-1/502:54:-1/1001:27:-1/3501:27:-1/1508:42:-1/3007:37:-1</dna>
  <dna>107/92/95/1/-29/40/-56/0/8/-5/6/19/94/5512:74:-1/5010:74:-1/4504:94:94/4004:66:94/6001:111:-1/2501:-1:-1/3001:-1:-1/3502:27:-1/1001:29:-1/1501:-1:-1/511:47:-1/2019:47:-1/7:9:-1</dna>
  <dna>113/94/100/-1/-15/25/-2/-18/3/0/12/13/101/5506:73:-1/5002:73:-1/4506:101:101/4006:62:101/6004:112:-1/507:50:-1/1:6:-1/1503:37:-1/2012:50:-1/3002:37:-1/1002:23:-1/3502:28:-1/2508:50:-1</dna>
  <dna>112/94/99/-1/-16/25/-18/0/10/-13/0/41/106/5501:86:-1/5001:86:-1/4515:106:106/4015:67:106/6001:111:-1/2503:46:-1/1:10:-1/502:46:-1/1501:-1:-1/1001:28:-1/3506:28:-1/2001:-1:-1/3006:47:-1</dna>
  <dna>111/94/95/5/-65/62/-5/-37/2/0/0/46/103/5503:77:-1/5006:77:-1/4501:103:103/4001:69:103/6003:111:-1/1505:37:-1/502:37:-1/4:15:-1/3506:34:-1/2503:37:-1/2009:53:-1/1001:34:-1/3005:37:-1</dna>
  <dna>108/93/93/2/-16/39/-15/0/6/-1/0/72/106/5507:79:-1/5001:79:-1/4507:106:106/4007:70:106/6004:109:-1/2501:-1:-1/3001:-1:-1/3503:21:-1/1:15:-1/1502:52:-1/2002:37:-1/502:39:-1/1001:33:-1</dna>
  <dna>111/94/97/5/-16/33/-15/-31/6/0/0/28/102/5509:81:-1/5008:81:-1/4509:102:102/4009:59:102/6004:109:-1/2015:42:-1/3008:42:-1/2505:42:-1/1006:22:-1/3506:22:-1/502:42:-1/7:4:-1/1502:42:-1</dna>
  <dna>100/90/88/15/-43/69/-52/0/11/0/63/28/106/5503:83:-1/5017:83:-1/4501:106:106/4001:71:106/6006:111:-1/2503:47:-1/2015:52:-1/1001:29:-1/1503:47:-1/3003:47:-1/3503:29:-1/514:47:-1/17:11:-1</dna>
  <dna>108/93/99/3/-54/38/-46/0/15/0/0/51/99/5502:74:-1/5002:74:-1/4501:99:99/4001:67:99/6004:109:-1/2501:-1:-1/1507:47:-1/3501:35:-1/3008:47:-1/8:3:-1/2015:47:-1/502:47:-1/1014:21:-1</dna>
  <dna>104/91/99/0/-24/25/-40/-39/2/0/15/54/108/5516:78:-1/5016:78:-1/4501:108:108/4001:56:108/6004:111:-1/2501:-1:-1/3501:33:-1/1005:21:-1/510:53:-1/2009:47:-1/1507:47:-1/3003:47:-1/3:17:-1</dna>

  <famousfairies>
	<!--
			_proportions[HEIGHT] / _proportions[HEAD] / _proportions[BODY] /
			_rotations[HEAD_ROT] / _rotations[UL_ARM_ROT] / _rotations[UR_ARM_ROT] / _rotations[LL_ARM_ROT] / _rotations[LR_ARM_ROT] / _rotations[UL_LEG_ROT] / _rotations[UR_LEG_ROT] / _rotations[LL_LEG_ROT] / _rotations[LR_LEG_ROT]
			_skinColorId /
			_itemTriplets ( id : color1 : color2 )
    -->
    <dna id="0" name="tinkerbell" fairyId="1000000001">100/95/88/0/-8/20/-15/0/12/0/0/28/106/34:6:-1/501:37:-1/1039:24:-1/1501:37:-1/2001:37:-1/2501:37:-1/3001:37:-1/3524:24:-1/4024:63:106/4524:106:-1/5022:73:-1/5528:73:-1/6005:165:-1</dna>
    <dna id="1" name="silvermist" fairyId="1000000002">100/95/88/0/-8/20/-15/0/12/0/0/28/108/36:6:-1/501:37:-1/1041:24:-1/1501:37:-1/2001:37:-1/2501:37:-1/3001:37:-1/3526:24:-1/4026:63:108/4526:108:-1/5024:73:-1/5530:73:-1/6004:112:-1</dna>
    <dna id="2" name="fawn" fairyId="1000000003">100/95/88/0/-8/20/-15/0/12/0/0/28/107/35:6:-1/536:37:-1/1040:24:-1/1501:37:-1/2001:37:-1/2501:37:-1/3001:37:-1/3525:24:-1/4025:63:107/4525:107:-1/5023:73:-1/5529:73:-1/6001:109:-1</dna>
    <dna id="3" name="rosetta" fairyId="1000000004">100/95/88/0/-8/20/-15/0/12/0/0/28/106/37:6:-1/501:37:-1/1042:24:-1/1501:37:-1/2001:37:-1/2501:37:-1/3001:37:-1/3527:24:-1/4027:63:106/4527:106:-1/5025:73:-1/5531:73:-1/6002:110:-1</dna>
    <dna id="4" name="iridessa" fairyId="1000000005">100/95/88/0/-8/20/-15/0/12/0/0/28/94/38:6:-1/501:37:-1/1043:24:-1/1501:37:-1/2001:37:-1/2501:37:-1/3001:37:-1/3528:24:-1/4028:63:94/4528:94:-1/5026:73:-1/5521:73:-1/6003:111:-1</dna>
    <dna id="5" name="tabby" fairyId="1000000006">100/95/88/0/-8/20/-15/0/12/0/0/28/102/32:6:-1/501:37:-1/1037:24:-1/1501:37:-1/2036:37:-1/2501:37:-1/3001:37:-1/3522:24:-1/4015:64:102/4504:102:-1/5021:73:-1/5527:73:-1/6004:109:-1</dna>
    <dna id="6" name="kit" fairyId="1000000008">100/95/88/0/-8/20/-15/0/12/0/0/28/101/33:6:-1/535:37:-1/1038:49:-1/1501:37:-1/2001:37:-1/2527:37:-1/3018:37:-1/3523:6:-1/4018:57:101/4518:101:-1/5017:81:-1/5522:81:-1/6004:109:-1</dna>
    <dna id="7" name="marina" fairyId="1000000007">100/95/88/0/-8/20/-15/0/12/0/0/28/95/272:6:166/501:37:-1/1223:49:166/1501:37:-1/2001:37:-1/2501:37:-1/3001:37:-1/3658:6:166/4013:60:95/4518:95:-1/5111:73:-1/5597:73:-1/6001:112:-1</dna>
    <dna id="8" name="sweetpea" fairyId="1000000009">100/95/88/0/-8/20/-15/0/12/0/0/28/103/31:6:-1/501:37:-1/1035:49:-1/1517:37:-1/2034:37:-1/2525:37:-1/3017:37:-1/3521:6:-1/4004:68:103/4518:103:-1/5015:85:-1/5524:85:-1/6003:110:-1</dna>
    <dna id="9" name="bellarose">99/105/91/0/-8/20/-22/-1/12/0/10/35/101/90:13:132/501:-1:-1/1143:55:111/1522:132:146/2097:132:146/2524:132:146/3002:13:-1/3569:13:101/4007:70:101/4511:101:102/5018:13:-1/5519:13:-1/6004:110:-1</dna>
    <dna id="10" name="brook">99/94/91/0/-8/20/-15/-10/6/0/0/28/94/248:128:185/571:113:185/1208:185:128/1501:13:-1/2054:113:128/2501:12:-1/3001:-1:-1/3614:113:166/4002:23:94/4509:94:-1/5001:76:76/5519:76:76/6003:112:-1</dna>
    <dna id="11" name="divawings">99/105/91/0/-8/20/-22/-1/12/0/10/35/93/3:55:-1/516:60:-1/1010:55:-1/1507:37:-1/2010:37:-1/2502:37:-1/3001:-1:-1/3507:55:-1/4011:141:93/4515:93:102/5010:76:-1/5508:76:-1/6005:112:-1</dna>
    <dna id="12" name="gale">100/95/88/0/-15/25/-15/0/12/0/0/28/107/15:499:-1/509:132:-1/1016:153:-1/1503:128:-1/2009:132:-1/2507:128:-1/3001:37:-1/3506:499:-1/4001:129:107/4501:107:-1/5018:109:-1/5504:109:-1/6003:128:-1</dna>
    <dna id="13" name="harmony">99/94/91/-6/-8/37/-15/-23/6/0/0/28/106/344:53:166/538:111:162/1009:44:166/1628:26:111/2285:53:111/2594:131:38/3001:-1:-1/3660:166:147/4007:57:106/4521:106:-1/5008:73:73/5510:73:73/6006:111:-1</dna>
    <dna id="14" name="trinket">99/94/91/0/-8/20/-15/-10/6/0/0/28/94/261:37:166/509:18:-1/1008:1:-1/1501:53:-1/2018:16:-1/2510:53:-1/3013:47:-1/3508:19:-1/4004:6:94/4504:94:-1/5015:90:-1/5517:90:-1/6005:165:-1</dna>
    <dna id="15" name="ember">100/95/88/0/-15/25/-15/0/12/0/0/28/107/25:128:-1/506:141:-1/1017:499:-1/1509:141:-1/2002:128:-1/2506:141:-1/3001:37:-1/3505:141:-1/4001:150:107/4501:107:-1/5008:141:-1/5509:141:-1/6003:128:-1</dna>
	<dna id="16" name="daisy">99/94/91/0/-8/20/-15/-10/6/0/0/28/104/343:55:181/501:1:166/1186:55:181/1501:54:166/2185:285:181/2501:54:166/3001:1:166/3742:181:55/4001:66:104/4514:104:-1/5019:78:78/5517:78:78/6005:110:-1</dna>
    <dna id="17" name="prism">99/94/91/0/-8/20/-15/-10/6/0/0/28/101/376:8:13/501:12:12/1294:31:8/1506:13:-1/2388:13:13/2501:-1:-1/3001:-1:-1/3716:26:13/4015:15:101/4515:101:-1/5017:80:80/5520:80:80/6004:110:-1</dna>
    <dna id="18" name="colette">107/97/88/0/-15/25/-15/0/12/0/0/28/107/41:22:18/533:18:22/1016:136:32/1519:136:149/2038:51:153/2524:22:-1/3013:37:-1/3530:42:24/4014:18:107/4505:107:-1/5018:37:-1/5513:37:-1/6001:112:-1</dna>
    <dna id="19" name="phoebe">107/97/88/0/-8/20/-15/-10/6/0/0/28/93/257:9:166/531:29:-1/1032:30:9/1515:13:30/2012:31:111/2519:157:-1/3006:9:-1/3519:31:30/4008:147:93/4515:93:-1/5009:73:-1/5522:73:-1/6006:111:-1</dna>
    <dna id="20" name="schelly">107/97/88/0/-15/25/-15/0/12/0/0/28/91/30:152:134/537:25:15/1044:14:32/1501:152:157/2015:72:134/2511:152:-1/3001:37:-1/3508:32:134/4008:60:91/4515:91:-1/5018:73:-1/5530:73:-1/6001:112:-1</dna>
    <dna id="21" name="water">100/95/88/0/-8/20/-15/0/12/0/0/28/107/1:6:-1/501:37:-1/1001:24:-1/1501:37:-1/2001:37:-1/2501:37:-1/3001:37:-1/3501:24:-1/4001:63:107/4501:107:-1/5001:73:-1/5501:73:-1/6001:112:-1</dna>
    <dna id="22" name="garden">100/95/88/0/-8/20/-15/0/12/0/0/28/102/1:8:-1/501:37:-1/1001:26:-1/1501:37:-1/2001:37:-1/2501:37:-1/3001:37:-1/3501:26:-1/4001:65:102/4501:102:-1/5001:82:-1/5501:82:-1/6001:110:-1</dna>
    <dna id="23" name="light">100/95/88/0/-8/20/-15/0/12/0/0/28/92/1:11:-1/501:37:-1/1001:29:-1/1501:37:-1/2001:37:-1/2501:37:-1/3001:37:-1/3501:29:-1/4001:57:92/4501:92:-1/5001:74:-1/5501:74:-1/6001:111:-1</dna>
    <dna id="24" name="animal">100/95/88/0/-8/20/-15/0/12/0/0/28/103/1:12:-1/501:37:-1/1001:30:-1/1501:37:-1/2001:37:-1/2501:37:-1/3001:37:-1/3501:30:-1/4001:58:103/4501:103:-1/5001:79:-1/5501:79:-1/6001:109:-1</dna>
    <dna id="25" name="tinker">100/95/88/0/-8/20/-15/0/12/0/0/28/103/1:2:-1/501:37:-1/1001:20:-1/1501:37:-1/2001:37:-1/2501:37:-1/3001:37:-1/3501:21:-1/4001:61:103/4501:103:-1/5001:90:-1/5501:90:-1/6001:165:-1</dna>
    <dna id="26" name="honey">99/105/88/12/-8/20/-29/0/12/0/41/29/94/1:11:29/502:28:166/1021:29:166/1502:27:166/2002:27:166/2501:18:-1/3001:39:-1/3506:30:166/4006:10:94/4506:94:-1/5010:78:-1/5517:78:-1/6001:111:166</dna>
    <dna id="27" name="rochelle">99/94/88/0/-8/20/-15/-10/6/0/0/28/100/261:72:166/512:5:-1/1011:33:-1/1501:38:-1/2015:51:-1/2513:5:-1/3001:18:-1/3513:32:166/4011:60:100/4511:100:-1/5028:74:-1/5523:74:-1/6004:112:-1</dna>
    <dna id="28" name="cassie">107/105/91/0/-8/20/-22/-1/12/0/10/35/103/89:49:24/501:12:-1/1004:49:-1/1501:53:-1/2001:13:-1/2501:47:-1/3001:47:-1/3542:49:51/4013:24:103/4519:107:-1/5010:43:-1/5519:43:-1/6002:109:-1</dna>
    <dna id="29" name="beck">103/109/95/0/-8/20/-15/0/12/0/0/28/107/92:6:166/549:37:166/1092:24:166/1524:37:166/2089:37:166/2501:37:166/3001:37:166/3566:24:166/4032:63:107/4532:107:-1/5041:73:-1/5544:73:-1/6003:166:166</dna>
    <dna id="30" name="elixa">100/95/88/0/-8/20/-15/0/12/0/0/28/96/98:6:-1/501:37:-1/1100:24:-1/1501:37:-1/2104:37:-1/2501:37:-1/3001:37:-1/3571:24:-1/4034:63:107/4534:96:-1/5043:73:-1/5546:73:-1/6003:166:166</dna>
    <dna id="31" name="coal">M/100/95/88/0/-12/15/-8/-10/-6/-2/0/15/94/123:19:46/501:37:166/1125:78:21/1501:37:166/2001:37:166/2501:37:-1/3001:37:-1/3583:77:21/4035:93:94/4537:94:-1/5056:77:-1/5547:77:-1/6001:112:166</dna>
    <dna id="32" name="gavin">M/100/95/88/0/-8/16/-15/-10/-2/-3/0/15/102/124:19:46/501:37:166/1126:78:21/1501:37:166/2001:37:166/2501:37:-1/3001:37:-1/3584:77:21/4035:24:102/4537:102:-1/5057:77:-1/5559:77:-1/6001:112:166</dna>
    <dna id="33" name="homeShop">M/100/95/88/0/0/10/-11/-18/0/0/2/28/102/171:-1:-1/572:37:166/1155:78:21/1501:37:166/2001:37:166/2501:37:-1/3001:37:-1/3609:77:21/4035:65:102/4551:102:-1/5072:77:-1/5547:77:-1/6001:112:166</dna>
    <dna id="34" name="clarion">100/95/88/0/-8/20/-15/-10/6/0/0/28/164/156:-1:-1/1146:-1:-1/4047:-1:-1/4556:164:-1/5073:-1:-1/5521:-1:-1/6007:-1:-1</dna>
    <dna id="35" name="terence">M/100/95/88/0/-8/20/-15/-10/6/0/0/28/106/166:19:46/1153:78:21/3600:77:21/4051:63:-1/4560:106:-1/5106:77:-1/5560:77:-1/6001:112:-1</dna>

    <!-- The DNA entries for crating hosts is in CraftingHost.xml -->
    <!-- These are just herre so support pulling them up in the fairy tool -->
    <dna id="36" name="bobbin">99/105/91/0/-8/20/-22/-1/12/0/10/35/100/132:170:21/537:33:34/1071:66:170/1501:53:-1/2007:170:-1/2501:47:-1/3001:47:-1/3506:33:-1/4006:58:100/4508:100:-1/5009:83:-1/5514:83:-1/6003:109:-1</dna>
    <dna id="37" name="mendy">100/95/91/0/-8/20/-22/-1/12/0/10/35/103/60:13:7/509:7:-1/1085:13:7/1501:53:-1/2112:13:-1/2501:47:-1/3001:47:-1/3507:55:-1/4001:10:103/4501:103:-1/5018:82:-1/5516:82:-1/6003:109:-1</dna>
    <dna id="38" name="dulcie">100/95/88/0/-8/20/-15/0/12/0/0/28/107/39:132:27/538:111:123/1044:27:81/1501:37:-1/2045:116:111/2509:111:166/3001:37:-1/3515:90:166/4005:91:107/4504:107:-1/5017:76:-1/5533:76:-1/6001:166:166</dna>
    <dna id="39" name="copper">100/95/88/0/-8/20/-15/0/12/0/0/28/93/21:127:166/537:84:77/1017:120:166/1511:83:166/2037:29:1/2501:37:-1/3011:83:166/3508:84:166/4001:84:93/4501:93:-1/5008:56:-1/5532:56:-1/6005:112:166</dna>

    <dna id="40" name="chloe">100/95/88/0/-8/20/-15/-10/6/0/0/28/87/274:6:166/501:37:-1/1225:24:166/1501:37:-1/2001:37:-1/2501:37:-1/3001:37:-1/3667:24:166/4052:63:87/4561:87:-1/5106:73:166/5521:73:166/6001:112:-1</dna>
    <dna id="41" name="zephyr">100/95/88/0/-8/20/-15/-10/6/0/0/28/107/301:6:166/501:37:166/1252:24:166/1501:37:-1/2001:26:27/2501:37:-1/3001:37:-1/3680:-1:-1/4005:39:107/4520:107:-1/5112:177:177/5566:177:177/6001:112:-1</dna>

    <dna id="42" name="spring">100/95/88/0/-8/24/-15/0/6/-1/0/28/102/338:6:166/501:37:-1/1275:24:166/1501:37:-1/2001:37:-1/2501:37:-1/3001:37:-1/3700:24:166/4001:2:102/4501:102:-1/5117:73:166/5600:73:166/6001:112:-1</dna>
	
	<dna id="43" name="erica">100/95/88/0/-8/20/-15/0/12/0/0/28/106/384:6:166/501:37:-1/1304:24:166/1501:37:-1/2298:37:166/2501:37:-1/3001:37:-1/3720:24:166/4001:63:106/4513:106:-1/5001:56:28/5507:56:28/6001:112:-1</dna>
	
	<dna id="44" name="periwinkle" fairyId="1000000023">100/95/88/0/-8/20/-15/0/6/0/0/32/108/494:6:166/501:37:-1/1410:24:166/1501:37:-1/2001:37:-1/2501:37:-1/3001:37:-1/3789:24:166/4052:63:108/4563:108:-1/5106:73:166/5521:73:166/6005:112:-1</dna>
	
	<dna id="45" name="spike">100/95/88/0/-8/20/-15/0/12/0/0/28/108/1000007:6:166/501:37:-1/1421:24:166/1501:37:-1/2001:37:-1/2501:37:-1/3001:37:-1/3796:24:166/4001:239:108/4503:108:-1/5125:55:42/5601:55:42/6001:112:-1</dna>
  </famousfairies>

  <catalogfairies>
	<dna id="blondeBigHair">100/95/88/0/-8/20/-15/0/2/0/0/24/108/1:6:166/501:37:-1/1001:24:-1/1501:37:-1/2001:37:-1/2501:37:-1/3001:37:-1/3501:24:166/4010:63:108/4511:108:-1/5012:109:-1/5509:109:-1/6006:112:166</dna>
	<dna id="wispy">100/95/88/0/-8/20/-15/0/6/0/0/24/109/1:6:166/501:37:-1/1001:24:-1/1501:37:-1/2001:37:-1/2501:37:-1/3001:37:-1/3501:24:166/4009:70:109/4519:107:-1/5034:73:-1/5539:73:-1/6005:-1:-1</dna>
	<dna id="glamourMane">100/95/88/0/-8/20/-15/0/6/0/0/24/92/1:6:166/501:37:-1/1001:24:-1/1501:37:-1/2001:37:-1/2501:37:-1/3001:37:-1/3501:24:166/4009:65:92/4505:92:-1/5008:76:-1/5538:76:-1/6002:-1:-1</dna>
	<dna id="sampleSparrow">M/100/95/88/0/-8/20/-15/-10/6/0/0/28/107/126:128:46/501:37:166/1120:128:21/1501:37:166/2001:37:166/2501:37:-1/3001:37:-1/3592:128:21/4035:63:107/4535:107:-1/5044:77:-1/5547:77:-1/6001:112:166</dna>

	<dna id="catalogFairy_1">100/95/88/0/-8/20/-15/0/12/0/0/28/108/1:6:166/501:37:-1/1001:24:-1/1501:37:-1/2001:37:-1/2501:37:-1/3001:37:-1/3501:24:-1/4004:62:108/4513:108:-1/5014:89:-1/5511:89:-1/6002:-1:-1</dna>
	<dna id="catalogFairy_2">100/95/88/0/-8/20/-15/0/12/0/0/28/105/1:6:166/501:37:-1/1001:24:-1/1501:37:-1/2001:37:-1/2501:37:-1/3001:37:-1/3501:24:-1/4008:66:105/4507:105:-1/5008:78:-1/5509:78:-1/6005:-1:-1</dna>
	<dna id="catalogFairy_3">100/95/88/0/-8/20/-15/-10/6/0/0/28/91/1:6:166/501:37:-1/1001:24:-1/1501:37:-1/2001:37:-1/2501:37:-1/3001:37:-1/3501:24:-1/4012:78:91/4512:91:-1/5009:191:-1/5539:191:-1/6003:112:166</dna>

	<dna id="catalogSparrow_1">M/100/95/88/0/-8/20/-15/-10/6/0/0/28/107/122:19:46/501:37:166/1120:78:21/1501:37:166/2001:-1:-1/2501:37:-1/3001:37:-1/3592:77:21/4037:6:107/4550:107:-1/5047:85:-1/5585:85:-1/6001:112:166</dna>
	<dna id="catalogSparrow_2">M/100/95/88/0/-8/20/-15/-10/6/0/0/28/98/122:19:46/501:37:166/1120:78:21/1501:37:166/2001:37:166/2501:37:-1/3001:37:-1/3592:77:21/4037:115:98/4536:98:-1/5052:78:-1/5555:78:-1/6003:-1:-1</dna>
	<dna id="catalogSparrow_3">M/100/95/88/0/-8/20/-15/-10/6/0/0/28/91/122:19:46/501:37:166/1120:78:21/1501:37:166/2001:37:166/2501:37:-1/3001:37:-1/3592:77:21/4037:78:91/4540:91:-1/5054:74:-1/5557:74:-1/6005:-1:-1</dna>
  </catalogfairies>

</pickledDNA>
